pythonryd.py
python_return_youtube_dislike-1.1.5.dist-info/LICENSE
python_return_youtube_dislike-1.1.5.dist-info/METADATA
python_return_youtube_dislike-1.1.5.dist-info/WHEEL
python_return_youtube_dislike-1.1.5.dist-info/top_level.txt
python_return_youtube_dislike-1.1.5.dist-info/RECORD
