Metadata-Version: 2.1
Name: python-return-youtube-dislike
Version: 1.1.5
Summary: A simple Python library to interact with the Return YouTube Dislike API
Author: Sean-e
Author-email: Sean-e <seane410@gmail.com>
Project-URL: Homepage, https://github.com/JrGamer410/Python-Return-YouTube-Dislike
Project-URL: Issues, https://github.com/JrGamer410/Python-Return-YouTube-Dislike/issues
Classifier: Programming Language :: Python :: 3
Classifier: License :: OSI Approved :: MIT License
Classifier: Operating System :: OS Independent
License-File: LICENSE
